coolpropx/__init__.py
coolpropx/bicubic/Verification_figures/T_inter_CP_error_contour.png
coolpropx/bicubic/Verification_figures/T_inter_CP_midpoint_error_contour.png
coolpropx/bicubic/Verification_figures/d_inter_CP_error_contour.png
coolpropx/bicubic/Verification_figures/d_inter_CP_midpoint_error_contour.png
coolpropx/bicubic/Verification_figures/k_inter_CP_error_contour.png
coolpropx/bicubic/Verification_figures/k_inter_CP_midpoint_error_contour.png
coolpropx/bicubic/Verification_figures/mu_inter_CP_error_contour.png
coolpropx/bicubic/Verification_figures/mu_inter_CP_midpoint_error_contour.png
coolpropx/bicubic/Verification_figures/s_inter_CP_error_contour.png
coolpropx/bicubic/Verification_figures/s_inter_CP_midpoint_error_contour.png
coolpropx/bicubic/generate_lookup_table.py
coolpropx/bicubic/generate_lookup_table_1.py
coolpropx/bicubic/generate_lookup_table_v2.py
coolpropx/bicubic/jax_bicubic_HEOS_interpolation_1.py
coolpropx/bicubic/plot_interpolated_coolprop_comparison.py
coolpropx/bicubic/plot_interpolated_der_FDcoolprop.py
coolpropx/bicubic/plot_interpolated_der_FDinterp.py
coolpropx/bicubic/plot_interpolated_midpoint_coolprop_comparison.py
coolpropx/bicubic/plot_interpolated_rawgrid_comparison.py
coolpropx/bicubic/plot_property_surface.py
coolpropx/core_calculations.py
coolpropx/fluid_properties.py
coolpropx/graphics.py
coolpropx/jax_import.py
coolpropx/jaxprop/__init__.py
coolpropx/jaxprop/jaxprop.py
coolpropx/math.py
coolpropx/perfect_gas/__init__.py
coolpropx/perfect_gas/perfect_gas.py
coolpropx/utils.py
coolpropx-0.2.14.dist-info/LICENSE.md
coolpropx-0.2.14.dist-info/METADATA
coolpropx-0.2.14.dist-info/WHEEL
coolpropx-0.2.14.dist-info/RECORD
