Metadata-Version: 2.1
Name: coolpropx
Version: 0.2.14
Summary: A lightweight wrapper to CoolProp's low-level interface.
Home-page: https://github.com/turbo-sim/coolpropx
License: MIT
Author: Roberto Agromayor
Requires-Python: >=3.10,<3.14
Classifier: License :: OSI Approved :: MIT License
Classifier: Programming Language :: Python :: 3
Classifier: Programming Language :: Python :: 3.10
Classifier: Programming Language :: Python :: 3.11
Classifier: Programming Language :: Python :: 3.12
Provides-Extra: jax
Requires-Dist: CoolProp (>=6.6.0,<7.0.0)
Requires-Dist: jax (>=0.5.3,<0.6.0) ; extra == "jax"
Requires-Dist: jaxlib (>=0.5.3,<0.6.0) ; extra == "jax"
Requires-Dist: matplotlib (>=3.10.1,<4.0.0)
Requires-Dist: numpy (>=2.2.4,<3.0.0)
Requires-Dist: pysolver_view (>=0.6.8,<0.7.0)
Requires-Dist: scipy (>=1.15.2,<2.0.0)
Project-URL: Documentation, https://github.com/turbo-sim/coolpropx
Project-URL: Repository, https://github.com/turbo-sim/coolpropx
